README.md
setup.py
cmdog.egg-info/PKG-INFO
cmdog.egg-info/SOURCES.txt
cmdog.egg-info/dependency_links.txt
cmdog.egg-info/entry_points.txt
cmdog.egg-info/requires.txt
cmdog.egg-info/top_level.txt
pkg/__init__.py
pkg/watchdog.py