Metadata-Version: 1.0
Name: cmdog
Version: 0.0.2
Summary: Monitor process operation
Home-page: UNKNOWN
Author: Jannchie
Author-email: jannchie@gmail.com
License: UNKNOWN
Platform: any
